{"sections":{"banner":{"type":"main-collection-banner","settings":{"color_scheme":"","overlay_opacity":20,"section_layout":"full","add_word":"Collection","show_word":false,"show_collection_description":true,"description_products":"description","image_size":"small","show_image":true,"subheading":"Subheading","subheading_second":"Subheading","margin_top":"no-indent","margin_bottom":"no-indent","padding_top":"m","padding_bottom":"xs"}},"product-grid":{"type":"main-collection-product-grid","settings":{"products_per_page":23,"show_secondary_image":true,"show_sku":true,"show_vendor":true,"show_collection_name":false,"show_desc":false,"show_color_swatch":true,"image_ratio":"portrait","image_fit":"cover","enable_filtering":true,"filter_type":"vertical","enable_sorting":true,"enable_per_row_button":true,"default_per_row":"small","image_filter_ratio":"4\/5","image_filter_fit":"cover","image_filter_columns":2,"padding_top":"xs","padding_bottom":"no-indent"}}},"order":["banner","product-grid"]}